{"names":["ประจักษ์-อัศวพลังพรหม"],"lawsuit":{"sec":[],"judgement":[],"nacc":[]},"relationship":[],"assets":{},"donation":[{"year":2554,"month":8,"date":null,"party":"เพื่อไทย","amount":10000000}],"business":[{"position":"คณะกรรมการบริษัท","business_name":"บริษัท มาร์วิน เทคโนโลยีส์ จำกัด","type":"(46599) การขายส่งเครื่องจักรและอุปกรณ์อื่นๆซึ่งมิได้จัดประเภทไว้ในที่อื่น"},{"position":"คณะกรรมการบริษัท","business_name":"บริษัท สีลมฮาร์ดแวร์ แอนด์ ซอฟต์แวร์ จำกัด","type":"(47524) ร้านขายปลีกวัสดุก่อสร้างอื่นๆ"},{"position":"กรรมการบริษัทและผู้ถือหุ้น","business_name":"ห้างหุ้นส่วนจำกัด แอฟโกไทย"}],"statement":{},"topAssets":{}}