{"age":null,"position":"สมาชิกสภาผู้แทนราษฎร (ส.ส.) พรรคอนาคตใหม่ สำนักงานเลขาธิการสภาผู้แทนราษฎร","previous_jobs":[{"company":{"title":"ร้านอาหาร มุมเหล้าตอง","agency":null,"address":"","sub_district":null,"district":"","province":"","post_code":null,"remark":null},"start_year":2560,"end_year":2562,"position_title":"เจ้าของกิจการ"},{"company":{"title":"ขายเสื้อมือ 2","agency":null,"address":"","sub_district":null,"district":"แม่สาย","province":"TH-57","post_code":null,"remark":null},"start_year":2558,"end_year":2560,"position_title":"ค้าขาย / กิจการส่วนตัว"}],"names":["พีรเดช-คำสมุทร"],"lawsuit":{"sec":[],"judgement":[],"nacc":[]},"relationship":[],"assets":{},"donation":[{"year":2562,"month":9,"date":null,"party":"อนาคตใหม่","amount":15000},{"year":2562,"month":10,"date":null,"party":"อนาคตใหม่","amount":15000},{"year":2562,"month":11,"date":null,"party":"อนาคตใหม่","amount":15000}],"business":[],"statement":{},"topAssets":{}}