{"names":["สุนิติ์-ทีวะเวช"],"lawsuit":{"sec":[],"judgement":[],"nacc":[]},"relationship":[],"assets":{},"donation":[{"year":2552,"month":6,"date":null,"party":"ประชาธิปัตย์","amount":5500},{"year":2552,"month":7,"date":null,"party":"ประชาธิปัตย์","amount":5500},{"year":2552,"month":8,"date":null,"party":"ประชาธิปัตย์","amount":5500},{"year":2552,"month":9,"date":null,"party":"ประชาธิปัตย์","amount":5500},{"year":2552,"month":10,"date":null,"party":"ประชาธิปัตย์","amount":5500},{"year":2552,"month":11,"date":null,"party":"ประชาธิปัตย์","amount":5500},{"year":2553,"month":1,"date":null,"party":"ประชาธิปัตย์","amount":5500},{"year":2553,"month":7,"date":null,"party":"ประชาธิปัตย์","amount":6400},{"year":2553,"month":9,"date":null,"party":"ประชาธิปัตย์","amount":6400},{"year":2553,"month":10,"date":null,"party":"ประชาธิปัตย์","amount":6400}],"business":[],"statement":{},"topAssets":{}}