{"lawsuit":{"sec":[],"judgement":[],"nacc":[]},"relationship":[],"assets":{},"donation":[{"year":2554,"month":3,"party":"ประชาธิปัตย์","amount":750000}],"business":[{"position":"คณะกรรมการบริษัท","business_name":"บริษัท โรงพยาบาลชลเวช จำกัด","type":"86101 กิจกรรมโรงพยาบาล"},{"position":"คณะกรรมการบริษัท","business_name":"บริษัท ไทย แอมดอน จำกัด","type":"32501 การผลิตเครื่องมือและอุปกรณ์ในทางการแพทย์ (ยกเว้นทางทันตกรรม)"},{"position":"คณะกรรมการบริษัท","business_name":"บริษัท สัตยบุตรอินเตอร์เนชั่นแนล จำกัด","type":"86101 กิจกรรมโรงพยาบาล"},{"position":"คณะกรรมการบริษัท","business_name":"บริษัท บางปะกงเวชชกิจ จำกัด","type":"86101 กิจกรรมโรงพยาบาล"},{"position":"คณะกรรมการบริษัท","business_name":"บริษัท โรงพยาบาลรวมแพทย์ฉะเชิงเทรา จำกัด","type":"86101 กิจกรรมโรงพยาบาล"}],"statement":{},"topAssets":{}}