[{"month":2,"year":2562,"donor_prefix":"บุคคลธรรมดา","donor_fullname":"สุเทพ คงเทศ","amount":499480},{"month":2,"year":2562,"donor_prefix":"บุคคลธรรมดา","donor_fullname":"ภักดี หิรัญ","amount":400000},{"month":2,"year":2562,"donor_prefix":"บุคคลธรรมดา","donor_fullname":"สุเทพ คงเทศ","amount":300000},{"month":3,"year":2562,"donor_prefix":"บุคคลธรรมดา","donor_fullname":"วีระพงศ์ สกล","amount":200000},{"month":3,"year":2562,"donor_prefix":"บุคคลธรรมดา","donor_fullname":"สุเทพ คงเทศ","amount":199780},{"month":2,"year":2562,"donor_prefix":"บุคคลธรรมดา","donor_fullname":"วีระพงศ์ สกล","amount":150000},{"month":3,"year":2562,"donor_prefix":"บุคคลธรรมดา","donor_fullname":"ภักดี หิรัญ","amount":100000},{"month":4,"year":2562,"donor_prefix":"บุคคลธรรมดา","donor_fullname":"พงศา ชูแนม","amount":100000},{"month":5,"year":2562,"donor_prefix":"บุคคลธรรมดา","donor_fullname":"พงศา ชูแนม","amount":100000},{"month":5,"year":2562,"donor_prefix":"บุคคลธรรมดา","donor_fullname":"พงศา ชูแนม","amount":100000},{"month":3,"year":2562,"donor_prefix":"บุคคลธรรมดา","donor_fullname":"พงศา ชูแนม","amount":30000},{"month":2,"year":2562,"donor_prefix":"บุคคลธรรมดา","donor_fullname":"สุทธิพงษ์ ธรรมวุฒิ","amount":20000},{"month":3,"year":2562,"donor_prefix":"นิติบุคคล","donor_fullname":"บริษัท ไชยาทรายเงิน จํากัด","amount":20000},{"month":2,"year":2562,"donor_prefix":"บุคคลธรรมดา","donor_fullname":"สมศักดิ์ สุขวงศ","amount":10000},{"month":2,"year":2562,"donor_prefix":"บุคคลธรรมดา","donor_fullname":"ประชา คุณธรรมดี","amount":5000},{"month":3,"year":2562,"donor_prefix":"บุคคลธรรมดา","donor_fullname":"สุเทพ คงเทศ","amount":5000}]