{"nacc":{"1":{"position":"สมาชิกสภาผู้แทนราษฎร (ส.ส.)","case":"กรณีพ้นจากตำแหน่ง","date":"2022-08-16T00:00:00.000Z","pdf":"https://storage.googleapis.com/act_datacatalog/corrupt0/co_003/001/pdf/pdf/วทันยา_บุนนาค_สมาชิกสภาผู้แทนราษฎร_(ส.ส.)_กรณีพ้นจากตำแหน่ง_13_ธ.ค._2565.pdf"}},"lawsuit":{"sec":[],"judgement":[],"nacc":[]},"relationship":[{"full_name":"สุรพันธ์ วงษ์โอภาสี","relationship_name":"บิดา"},{"full_name":"มะลิวัลย์ วงศ์ชินศรี","relationship_name":"มารดา"},{"full_name":"ณัฏฐ์ วงษ์โอภาสี","relationship_name":"พี่น้อง"},{"full_name":"ภควันต์ วงษ์โอภาสี","relationship_name":"พี่น้อง"},{"full_name":"พอใจ บุนนาค","relationship_name":"บุตร"},{"full_name":"พอเพียง บุนนาค","relationship_name":"บุตร"},{"full_name":"ฉาย บุนนาค","relationship_name":"คู่สมรส"}],"assets":{"1":{"ที่ดิน":[{"actor":"ผู้ยื่น","value":10080000,"type":"โฉนด","name":"โฉนดที่ดิน","address":"คลองตัน พระโขนง กรุงเทพมหานคร","land_doc_number":114172,"receiveDate":"6/7/2554"},{"actor":"ผู้ยื่น","value":10080000,"type":"โฉนด","name":"โฉนดที่ดิน","address":"คลองตัน พระโขนง กรุงเทพมหานคร","land_doc_number":114173,"receiveDate":"26/9/2554"},{"actor":"ผู้ยื่น","value":10080000,"type":"โฉนด","name":"โฉนดที่ดิน","address":"คลองตัน พระโขนง กรุงเทพมหานคร","land_doc_number":114174,"receiveDate":"6/7/2555"},{"actor":"ผู้ยื่น","value":1837500,"type":"โฉนด","name":"โฉนดที่ดิน","address":"บึงกุ่ม บึงกุ่ม กรุงเทพมหานคร","land_doc_number":23111,"receiveDate":"10/10/2556"},{"actor":"ผู้ยื่น","value":2925000,"type":"โฉนด","name":"โฉนดที่ดิน","address":"ดอกไม้ พระโขนง กรุงเทพมหานคร","land_doc_number":62167,"receiveDate":"25/3/2548"},{"actor":"ผู้ยื่น","value":104000000,"type":"โฉนด","name":"โฉนดที่ดิน","address":"คลองตัน พระโขนง กรุงเทพมหานคร","land_doc_number":16157,"receiveDate":"16/10/2561"},{"actor":"ผู้ยื่น","value":10640000,"type":"โฉนด","name":"โฉนดที่ดิน","address":"คลองตัน พระโขนง กรุงเทพมหานคร","land_doc_number":114175,"receiveDate":"10/6/2565"}],"โรงเรือนและสิ่งปลูกสร้าง":[{"actor":"ผู้ยื่น","value":92000000,"type":"ห้องชุด","name":"ห้องชุดเพนท์เฮ้าส์","address":"คลองตันเหนือ วัฒนา กรุงเทพมหานคร","building_doc_number":"2500","receiveDate":"31/7/2560"},{"actor":"ผู้ยื่น","value":16500000,"type":"ห้องชุด","name":"ห้องชุด","address":"คลองตันเหนือ วัฒนา กรุงเทพมหานคร","building_doc_number":"320,321,322,329,324","receiveDate":"20/12/2553"},{"actor":"ผู้ยื่น","value":630000,"type":"บ้าน","name":"ทาวน์เฮ้าส์","address":"คลองตันเหนือ วัฒนา กรุงเทพมหานคร","building_doc_number":"114172","receiveDate":"6/7/2554"},{"actor":"ผู้ยื่น","value":2076460,"type":"บ้าน","name":"บ้านเดี่ยว 3 ชั้น","address":"นวมินทร์ บึงกุ่ม กรุงเทพมหานคร","building_doc_number":"23111","receiveDate":"10/10/2556"},{"actor":"ผู้ยื่น","value":7500000,"type":"ห้องชุด","name":"ห้องชุด","address":"พระโขนง พระโขนง กรุงเทพมหานคร","building_doc_number":"7124, 7125, 7316, 11852, 176836-176844","receiveDate":"26/2/2553"},{"actor":"ผู้ยื่น","value":656180,"type":"บ้าน","name":"บ้านเดี่ยว","address":"คลองตันเหนือ วัฒนา กรุงเทพมหานคร","building_doc_number":"16157","receiveDate":"16/10/2561"},{"actor":"ผู้ยื่น","value":580440,"type":"บ้าน","name":"ทาวน์เฮาส์","address":"คลองตันเหนือ วัฒนา กรุงเทพมหานคร","building_doc_number":"114175","receiveDate":"10/6/2565"}],"ยานพาหนะ":[{"actor":"ผู้ยื่น","value":18900,"type":"จักรยานยนต์","name":"จักรยานยนต์","address":"","registration_number":"1กค5025","receiveDate":"29/8/2556","province":"นครราชสีมา"},{"actor":"ผู้ยื่น","value":2800000,"type":"รถยนต์","name":"รถยนต์","address":"","registration_number":"นบ55","receiveDate":"2/4/2562","province":"กรุงเทพมหานคร"},{"actor":"ผู้ยื่น","value":2150000,"type":"รถยนต์","name":"รถยนต์","address":"","registration_number":"ญภ5566","receiveDate":"10/10/2557","province":"กรุงเทพมหานคร"},{"actor":"ผู้ยื่น","value":2280000,"type":"รถยนต์","name":"รถยนต์","address":"","registration_number":"1นก1327","receiveDate":"21/2/2562","province":"กรุงเทพมหานคร"},{"actor":"ผู้ยื่น","value":2068000,"type":"รถยนต์","name":"รถยนต์","address":"","registration_number":"ฉบ999","receiveDate":"11/10/2562","province":"กรุงเทพมหานคร"},{"actor":"ผู้ยื่น","value":5500000,"type":"รถยนต์","name":"รถยนต์","address":"","registration_number":"สฬ6655","receiveDate":"24/4/2564","province":"กรุงเทพมหานคร"}],"สิทธิและสัมปทาน":[{"actor":"ผู้ยื่น","value":3685117.81,"type":"กรมธรรม์","name":"สิทธิในกรมธรรม์ประกันภัย เลขที่ 5055394217 บริษัท เมืองไทยประกันชีวิต จำกัด (มหาชน)","address":"","receiveDate":"30/6/2553","endDate":"30/6/2567"},{"actor":"ผู้ยื่น","value":245098.88,"type":"กรมธรรม์","name":"สิทธิในกรมธรรม์ประกันภัย เลขที่ T142753985 บริษัท เอไอเอ จำกัด","address":"","receiveDate":"26/6/2551","endDate":"26/6/2571"},{"actor":"ผู้ยื่น","value":196151.85,"type":"กรมธรรม์","name":"สิทธิในกรมธรรม์ประกันภัย เลขที่ T105268268 บริษัท เอไอเอ จำกัด","address":"","receiveDate":"2/9/2546","endDate":"2/9/2588"},{"actor":"ผู้ยื่น","value":238702.78,"type":"กรมธรรม์","name":"สิทธิในกรมธรรม์ประกันภัย เลขที่ T144092495 บริษัท เอไอเอ จำกัด","address":"","receiveDate":"29/12/2551","endDate":"29/12/2571"},{"actor":"ผู้ยื่น","value":335532.86,"type":"กรมธรรม์","name":"สิทธิในกรมธรรม์ประกันภัย เลขที่ T144092466 บริษัท เอไอเอ จำกัด","address":"","receiveDate":"4/12/2551","endDate":"4/12/2571"},{"actor":"ผู้ยื่น","value":4659813.7,"type":"กรมธรรม์","name":"สิทธิในกรมธรรม์ประกันภัย เลขที่ 100001646469 บริษัท เอฟดับบลิวดี ประกันชีวิต จำกัด (มหาชน)","address":"","receiveDate":"3/4/2558","endDate":"3/4/2570"},{"actor":"ผู้ยื่น","value":702000,"type":"กองทุน","name":"กองทุนเพื่อผู้เคยเป็นสมาชิกรัฐสภา สำนักงานเลขาธิการสภาผู้แทนราษฎร","address":"","receiveDate":"16/8/2565","endDate":"15/2/2572"},{"actor":"ผู้ยื่น","value":110667,"type":"อื่นๆ","name":"เงินสงเคราะห์ชราภาพมาตรา 33/39 สำนักงานประกันสังคม","address":""},{"actor":"ผู้ยื่น","value":0,"type":"สมาชิก","name":"สิทธิในสมาชิก แปซิฟิค คลับ ซิตี้ หมายเลขสมาชิก W0167","address":"","receiveDate":"9/2/2564"},{"actor":"ผู้ยื่น","value":480966.88,"type":"กรมธรรม์","name":"สิทธิในกรมธรรม์ประกันภัย เลขที่ T126026146 บริษัท เอไอเอ จำกัด","address":"","receiveDate":"21/11/2549","endDate":"21/11/2574"},{"actor":"ผู้ยื่น","value":290.4,"type":"กรมธรรม์","name":"สิทธิในกรมธรรม์ประกันภัย เลขที่ T134233497 บริษัท เอไอเอ จำกัด","address":"","receiveDate":"28/9/2550","endDate":"12/11/2565"},{"actor":"ผู้ยื่น","value":243631.78,"type":"กรมธรรม์","name":"สิทธิในกรมธรรม์ประกันภัย เลขที่ 4403184 บริษัท เอฟดับบลิวดี ประกันชีวิต จำกัด (มหาชน)","address":"","receiveDate":"23/11/2548","endDate":"23/11/2573"},{"actor":"ผู้ยื่น","value":1964383.56,"type":"กรมธรรม์","name":"สิทธิในกรมธรรม์ประกันภัย เลขที่ 9443813 บริษัท เอฟดับบลิวดี ประกันชีวิต จำกัด (มหาชน)","address":"","receiveDate":"19/12/2551","endDate":"19/12/2565"},{"actor":"ผู้ยื่น","value":955265.75,"type":"กรมธรรม์","name":"สิทธิในกรมธรรม์ประกันภัย เลขที่ 11704889 บริษัท เอฟดับบลิวดี ประกันชีวิต จำกัด (มหาชน)","address":"","receiveDate":"26/6/2552","endDate":"26/6/2566"},{"actor":"ผู้ยื่น","value":99082.62,"type":"กรมธรรม์","name":"สิทธิในกรมธรรม์ประกันภัย เลขที่ 40670760 บริษัท เอฟดับบลิวดี ประกันชีวิต จำกัด (มหาชน)","address":"","receiveDate":"22/11/2562","endDate":"22/11/2576"},{"actor":"ผู้ยื่น","value":3658602.74,"type":"กรมธรรม์","name":"สิทธิในกรมธรรม์ประกันภัย เลขที่ 5056599046 บริษัท เมืองไทยประกันชีวิต จำกัด (มหาชน)","address":"","receiveDate":"30/9/2553","endDate":"30/9/2567"},{"actor":"ผู้ยื่น","value":123442.78,"type":"อื่นๆ","name":"เงินสงเคราะห์ชราภาพมาตรา 33/39 สำนักงานประกันสังคม","address":"","endDate":"13/9/2566"},{"actor":"ผู้ยื่น","value":215392.59,"type":"กรมธรรม์","name":"สิทธิในกรมธรรม์ประกันภัย เลขที่ T154160922 บริษัท เอไอเอ จำกัด","address":"","receiveDate":"25/2/2554","endDate":"25/2/2579"},{"actor":"ผู้ยื่น","value":106827.97,"type":"กรมธรรม์","name":"สิทธิในกรมธรรม์ประกันภัย เลขที่ T173893157 บริษัท เอไอเอ จำกัด","address":"","receiveDate":"6/7/2555","endDate":"6/7/2632"},{"actor":"ผู้ยื่น","value":1891309.59,"type":"กรมธรรม์","name":"สิทธิในกรมธรรม์ประกันภัย เลขที่ 5053068060 บริษัท เมืองไทยประกันชีวิต จำกัด (มหาชน)","address":"","receiveDate":"25/11/2552","endDate":"25/11/2566"},{"actor":"ผู้ยื่น","value":210368.49,"type":"กรมธรรม์","name":"สิทธิในกรมธรรม์ประกันภัย เลขที่ T164870325 บริษัท เอไอเอ จำกัด","address":"","receiveDate":"23/5/2554","endDate":"23/5/2579"},{"actor":"ผู้ยื่น","value":284251.78,"type":"กรมธรรม์","name":"สิทธิในกรมธรรม์ประกันภัย เลขที่ 40481424 บริษัท เอฟดับบลิวดี ประกันชีวิต จำกัด (มหาชน)","address":"","receiveDate":"30/10/2561","endDate":"30/10/2576"},{"actor":"ผู้ยื่น","value":906466.75,"type":"กรมธรรม์","name":"สิทธิในกรมธรรม์ประกันภัย เลขที่ 3009605009 บริษัท อลิอันซ์ อยุธยา ประกันชีวิต จำกัด (มหาชน)","address":"","receiveDate":"27/12/2553","endDate":"27/12/2568"},{"actor":"ผู้ยื่น","value":0,"type":"สมาชิก","name":"สิทธิในสมาชิก The Racquet Club หมายเลข 19054","address":"","receiveDate":"26/4/2565","endDate":"26/4/2566"},{"actor":"ผู้ยื่น","value":0,"type":"สมาชิก","name":"สิทธิในสมาชิก The Racquet Club หมายเลข 19055","address":"","receiveDate":"26/4/2565","endDate":"26/4/2566"},{"actor":"ผู้ยื่น","value":0,"type":"สมาชิก","name":"สิทธิในสมาชิก The Racquet Club หมายเลข 13511","address":"","receiveDate":"26/4/2565","endDate":"26/4/2566"},{"actor":"ผู้ยื่น","value":0,"type":"สมาชิก","name":"สิทธิในสมาชิกในราชกรีฑาสโมสร หมายเลข 9905020384","address":""},{"actor":"ผู้ยื่น","value":0,"type":"สมาชิก","name":"สิทธิในสมาชิก Pacific Club ตลอดชีพ","address":"","receiveDate":"11/4/2562"}],"ทรัพย์สินอื่น":{"กระเป๋า":[{"actor":"ผู้ยื่น","value":3100000,"type":"กระเป๋า","name":"กระเป๋า Hermes รุ่น Himalayan Birkin","address":"","count":1},{"actor":"ผู้ยื่น","value":465900,"type":"กระเป๋า","name":"กระเป๋า Hermes รุ่น Kelly Size 32 สี Eleetra blue","address":"","count":1},{"actor":"ผู้ยื่น","value":575000,"type":"กระเป๋า","name":"กระเป๋า Hermes รุ่น Kelly Size 32 สี Rose Lipstick","address":"","count":1},{"actor":"ผู้ยื่น","value":496952,"type":"กระเป๋า","name":"กระเป๋า Hermes รุ่น Kelly Size 32 สี Black","address":"","count":1},{"actor":"ผู้ยื่น","value":400000,"type":"กระเป๋า","name":"กระเป๋า Hermes รุ่น Kelly Size 32 สี Natural","address":"","count":1},{"actor":"ผู้ยื่น","value":400000,"type":"กระเป๋า","name":"กระเป๋า Hermes รุ่น Birkin Size 25 สี Etoupe","address":"","count":1},{"actor":"ผู้ยื่น","value":140000,"type":"กระเป๋า","name":"กระเป๋า Hermes รุ่น Toolbox สีน้ำตาล","address":"","count":1},{"actor":"ผู้ยื่น","value":119000,"type":"กระเป๋า","name":"กระเป๋า Hermes รุ่น Jypsiere สีน้ำตาล","address":"","count":1},{"actor":"ผู้ยื่น","value":300000,"type":"กระเป๋า","name":"กระเป๋า Hermes รุ่น Birkin Size 30 สีเทา","address":"","count":1},{"actor":"ผู้ยื่น","value":200000,"type":"กระเป๋า","name":"กระเป๋า Hermes รุ่น Kelly Size 32 สีส้ม","address":"","count":1},{"actor":"ผู้ยื่น","value":170000,"type":"กระเป๋า","name":"กระเป๋า Hermes รุ่น Lindy สีน้ำเงิน","address":"","count":1},{"actor":"ผู้ยื่น","value":359000,"type":"กระเป๋า","name":"กระเป๋า Hermes รุ่น Kelly Size 28 สี Indigo Blue","address":"","count":1},{"actor":"ผู้ยื่น","value":62900,"type":"กระเป๋า","name":"กระเป๋า Hermes รุ่น Everlyn สีชมพู","address":"","count":1},{"actor":"ผู้ยื่น","value":190790,"type":"กระเป๋า","name":"กระเป๋า Chanel รุ่น Classic Size Jumbo สี Beige","address":"","count":1},{"actor":"ผู้ยื่น","value":190790,"type":"กระเป๋า","name":"กระเป๋า Chanel รุ่น Classic Size Jumbo สี Black","address":"","count":1},{"actor":"ผู้ยื่น","value":119650,"type":"กระเป๋า","name":"กระเป๋า Chanel รุ่น Classic Size 10 สี Red","address":"","count":1},{"actor":"ผู้ยื่น","value":179000,"type":"กระเป๋า","name":"กระเป๋า Chanel รุ่น Reissue สี Champagne","address":"","count":1},{"actor":"ผู้ยื่น","value":82500,"type":"กระเป๋า","name":"กระเป๋า Chanel รุ่น Reissue Roll Clutch lambskin","address":"","count":1},{"actor":"ผู้ยื่น","value":69000,"type":"กระเป๋า","name":"กระเป๋า Givenchy รุ่น Pandora","address":"","count":1},{"actor":"ผู้ยื่น","value":88000,"type":"กระเป๋า","name":"กระเป๋า Givenchy รุ่น GV3 ไซส์ Medium สีดำ","address":"","count":1},{"actor":"ผู้ยื่น","value":83390,"type":"กระเป๋า","name":"กระเป๋า Valentino รุ่น Medium Rockstud Crossbody","address":"","count":1},{"actor":"ผู้ยื่น","value":120000,"type":"กระเป๋า","name":"กระเป๋า Valentino รุ่น Rockstud หนัง Stringray","address":"","count":1},{"actor":"ผู้ยื่น","value":160000,"type":"กระเป๋า","name":"กระเป๋า Celine รุ่น Box Stingray Exotic","address":"","count":1},{"actor":"ผู้ยื่น","value":120000,"type":"กระเป๋า","name":"กระเป๋า Celine รุ่น Tie สีน้ำเงิน","address":"","count":1},{"actor":"ผู้ยื่น","value":58000,"type":"กระเป๋า","name":"กระเป๋า Boyy รุ่น Bobby ไซส์ 23 หนังงู","address":"","count":1},{"actor":"ผู้ยื่น","value":37200,"type":"กระเป๋า","name":"กระเป๋า Boyy รุ่น Karl Leopard","address":"","count":1},{"actor":"ผู้ยื่น","value":73500,"type":"กระเป๋า","name":"กระเป๋า Balenciaga รุ่น Riva City สี Cognac","address":"","count":1},{"actor":"ผู้ยื่น","value":165550,"type":"กระเป๋า","name":"กระเป๋า Fendi รุ่น Peekaboo Iconic Essential","address":"","count":1},{"actor":"ผู้ยื่น","value":193390,"type":"กระเป๋า","name":"กระเป๋า Bottega Veneta รุ่น Intrecciato Calf Roma สี China Red","address":"","count":1},{"actor":"ผู้ยื่น","value":100000,"type":"กระเป๋า","name":"กระเป๋า Christian Dior รุ่น zippy หนังงู","address":"","count":69}],"นาฬิกา":[{"actor":"ผู้ยื่น","value":1089000,"type":"นาฬิกา","name":"นาฬิกา Patek Philippe","address":"","count":3},{"actor":"ผู้ยื่น","value":175400,"type":"นาฬิกา","name":"นาฬิกา Panerai","address":"","count":9},{"actor":"ผู้ยื่น","value":1017000,"type":"นาฬิกา","name":"นาฬิกา Rolex รุ่น Daytona สี Rose Gold","address":"","count":1},{"actor":"ผู้ยื่น","value":300000,"type":"นาฬิกา","name":"นาฬิกา Rolex รุ่น Oyster Perpetual","address":"","count":1},{"actor":"ผู้ยื่น","value":330000,"type":"นาฬิกา","name":"นาฬิกา Rolex รุ่น Oyster Perpetual","address":"","count":1},{"actor":"ผู้ยื่น","value":275000,"type":"นาฬิกา","name":"นาฬิกา Rolex รุ่น Oyster Perpetual","address":"","count":1},{"actor":"ผู้ยื่น","value":500000,"type":"นาฬิกา","name":"นาฬิกา Hublot","address":"","count":1},{"actor":"ผู้ยื่น","value":2221000,"type":"นาฬิกา","name":"นาฬิกา Breguet","address":"","count":1},{"actor":"ผู้ยื่น","value":180000,"type":"นาฬิกา","name":"นาฬิกา Penerai","address":"","count":1},{"actor":"ผู้ยื่น","value":150000,"type":"นาฬิกา","name":"นาฬิกา Omega Speedmaster","address":"","count":1},{"actor":"ผู้ยื่น","value":500000,"type":"นาฬิกา","name":"นาฬิกา Rolex GMT-MASTER II","address":"","count":1}],"เครื่องประดับ":[{"actor":"ผู้ยื่น","value":730000,"type":"เครื่องประดับ","name":"แหวนเพชร 1.5 กะรัต","address":"","count":1},{"actor":"ผู้ยื่น","value":350000,"type":"เครื่องประดับ","name":"แหวนเพชร","address":"","count":1},{"actor":"ผู้ยื่น","value":50000,"type":"เครื่องประดับ","name":"แหวนเพชร","address":"","count":1},{"actor":"ผู้ยื่น","value":323200,"type":"เครื่องประดับ","name":"กำไลข้อมือ Catire รุ่น Love","address":"","count":1},{"actor":"ผู้ยื่น","value":240000,"type":"เครื่องประดับ","name":"แหวน Catier รุ่น Paris Nouvelle Vague","address":"","count":1},{"actor":"ผู้ยื่น","value":200000,"type":"เครื่องประดับ","name":"สร้อยเพชรพร้อมจี้เพชรรูปหัวใจ","address":"","count":1},{"actor":"ผู้ยื่น","value":20000,"type":"เครื่องประดับ","name":"แหวนทับทิม","address":"","count":1},{"actor":"ผู้ยื่น","value":100000,"type":"เครื่องประดับ","name":"แหวนมรกต","address":"","count":1},{"actor":"ผู้ยื่น","value":200000,"type":"เครื่องประดับ","name":"ต่างหูมรกต 1 คู่","address":"","count":1},{"actor":"ผู้ยื่น","value":19000,"type":"เครื่องประดับ","name":"แหวนเพชร 0.3 กะรัต","address":"","count":1},{"actor":"ผู้ยื่น","value":450000,"type":"เครื่องประดับ","name":"แหวนเพชรทรงเหลื่ยม ขนาด 1.16 กะรัต","address":"","count":1},{"actor":"ผู้ยื่น","value":466000,"type":"เครื่องประดับ","name":"แหวนเพชรทรงกลม ขนาด 1.2 กะรัต","address":"","count":1},{"actor":"ผู้ยื่น","value":20000,"type":"เครื่องประดับ","name":"แหวนเพชรรูปดอกไม้เรือนทองคำ","address":"","count":1},{"actor":"ผู้ยื่น","value":15000,"type":"เครื่องประดับ","name":"แหวนประดับมุก","address":"","count":1},{"actor":"ผู้ยื่น","value":120000,"type":"เครื่องประดับ","name":"แหวน PG ฉลุใบมะขาม เขียวส่อง เพชร บุษราคัม","address":"","count":1},{"actor":"ผู้ยื่น","value":91000,"type":"เครื่องประดับ","name":"เพชร น้ำหนัก 0.91 กะรัต (G)","address":"","count":1},{"actor":"ผู้ยื่น","value":91000,"type":"เครื่องประดับ","name":"เพชร น้ำหนัก 0.91 กะรัต (G)","address":"","count":1},{"actor":"ผู้ยื่น","value":100000,"type":"เครื่องประดับ","name":"สร้อยคอไข่มุก MIKIMOTO รุ่น KZ713","address":"","count":1},{"actor":"ผู้ยื่น","value":180000,"type":"เครื่องประดับ","name":"สร้อยคอไข่มุก MIKIMOTO","address":"","count":1},{"actor":"ผู้ยื่น","value":860000,"type":"เครื่องประดับ","name":"สร้อยคอไข่มุก MIKIMOTO","address":"","count":1},{"actor":"ผู้ยื่น","value":15000,"type":"เครื่องประดับ","name":"ต่างหูผึ้ง ปีกเพชร 1 คู่","address":"","count":1},{"actor":"ผู้ยื่น","value":68000,"type":"เครื่องประดับ","name":"สร้อยข้อมูลเพชร ตัวเรือนทองคำขาว 18K","address":"","count":1},{"actor":"ผู้ยื่น","value":250000,"type":"เครื่องประดับ","name":"ต่างหูเพชร","address":"","count":1},{"actor":"ผู้ยื่น","value":59000,"type":"เครื่องประดับ","name":"ต่างหูเพชร ตัวเรือนทองคำขาว","address":"","count":1},{"actor":"ผู้ยื่น","value":100000,"type":"เครื่องประดับ","name":"เพชร น้ำหนัก 0.83 กะรัต (E)","address":"","count":1},{"actor":"ผู้ยื่น","value":20000,"type":"เครื่องประดับ","name":"กำไลหยก","address":"","count":1},{"actor":"ผู้ยื่น","value":150000,"type":"เครื่องประดับ","name":"สร้อยไข่มุกดำ","address":"","count":1},{"actor":"ผู้ยื่น","value":30000,"type":"เครื่องประดับ","name":"สร้อยไข่มุก","address":"","count":1},{"actor":"ผู้ยื่น","value":45000,"type":"เครื่องประดับ","name":"สร้อยไข่มุกเล็ก","address":"","count":1},{"actor":"ผู้ยื่น","value":45000,"type":"เครื่องประดับ","name":"จี้หยกล้อมเพชร","address":"","count":1},{"actor":"ผู้ยื่น","value":50000,"type":"เครื่องประดับ","name":"ชุดหยกล้อมเพขร","address":"","count":1},{"actor":"ผู้ยื่น","value":20000,"type":"เครื่องประดับ","name":"ต่างหูเพชร","address":"","count":1},{"actor":"ผู้ยื่น","value":90000,"type":"เครื่องประดับ","name":"แหวนเพชร","address":"","count":1},{"actor":"ผู้ยื่น","value":300000,"type":"เครื่องประดับ","name":"ชุดเครื่องเพชร","address":"","count":1},{"actor":"ผู้ยื่น","value":25000,"type":"เครื่องประดับ","name":"แหวนบุษราคัม","address":"","count":1},{"actor":"ผู้ยื่น","value":40000,"type":"เครื่องประดับ","name":"แหวนทองประดับเพชร","address":"","count":1},{"actor":"ผู้ยื่น","value":385500,"type":"เครื่องประดับ","name":"ทองคำรูปพรรณกึ่งจิวเวอร์รี่","address":"","count":1},{"actor":"ผู้ยื่น","value":353000,"type":"เครื่องประดับ","name":"กำไล Cartier","address":"","count":1,"receiveDate":"5/6/2565"},{"actor":"ผู้ยื่น","value":505000,"type":"เครื่องประดับ","name":"สร้อยคอ TIFFANY&CO","address":"","count":1,"receiveDate":"10/6/2565"}],"วัตถุมงคล":[{"actor":"ผู้ยื่น","value":18150000,"type":"วัตถุมงคล","name":"พระเครื่อง หลวงพ่อแก้ว วัดเครือวัลย์ พิมพ์กลาง 1 พร้อมกรอบทองล้อมเพชร","address":"","count":1},{"actor":"ผู้ยื่น","value":45200000,"type":"วัตถุมงคล","name":"พระเครื่อง สมเด็จ วัดระฆัง พิมพ์ใหญ่ พร้อมกรอบทองล้อมเพชร","address":"","count":1},{"actor":"ผู้ยื่น","value":12150000,"type":"วัตถุมงคล","name":"พระเครื่อง หลวงพ่อแก้ว วัดเครือวัลย์ พิมพ์กลาง 2 พร้อมกรอบทองล้อมเพชร","address":"","count":1},{"actor":"ผู้ยื่น","value":10000000,"type":"วัตถุมงคล","name":"พระเครื่อง ซุ้มกอ","address":"","count":1},{"actor":"ผู้ยื่น","value":1650000,"type":"วัตถุมงคล","name":"พระเครื่อง หลวงพ่อคลีพ วัดสมถะ จังหวัดชลบุรี พร้อมกรอบทองล้อมเพชร","address":"","count":1},{"actor":"ผู้ยื่น","value":1150000,"type":"วัตถุมงคล","name":"พระเครื่อง เหรียญวัดพนัญเชิง พร้อมกรอบทองล้อมเพชร","address":"","count":1},{"actor":"ผู้ยื่น","value":1000000,"type":"วัตถุมงคล","name":"พระเครื่อง หลวงปู่ทวดเนื้อว่าน วัดช้างไห้","address":"","count":1},{"actor":"ผู้ยื่น","value":1500000,"type":"วัตถุมงคล","name":"พระเครื่อง หลวงปู่ทวด วัดช้างไห้ พิมพ์กลาง ไม่ปั๊มซ้ำ","address":"","count":1},{"actor":"ผู้ยื่น","value":2100000,"type":"วัตถุมงคล","name":"พระเครื่อง หลวงพ่อแก้ว วัดเครือวัลย์ พิมพ์จิ๋ว พร้อมกรอบทองล้อมเพชร","address":"","count":1},{"actor":"ผู้ยื่น","value":8000000,"type":"วัตถุมงคล","name":"พระพุทธรูปปางลีลา สุโขทัย","address":"","count":1},{"actor":"ผู้ยื่น","value":20000000,"type":"วัตถุมงคล","name":"พระพุทธรูปอู่ทอง หน้าหนุ่ม","address":"","count":1},{"actor":"ผู้ยื่น","value":2500000,"type":"วัตถุมงคล","name":"พระลีลากำแพงศอก กรุวัดพระศรีรัตนมหาธาตุ จังหวัดสุพรรณบุรี","address":"","count":1},{"actor":"ผู้ยื่น","value":200000,"type":"วัตถุมงคล","name":"องค์จตุคาม รุ่นปี 2530","address":"","count":1},{"actor":"ผู้ยื่น","value":2000000,"type":"วัตถุมงคล","name":"สมเด็จวัดเกศไชโย พิมพ์นิยม ฐาน 7 ชั้น","address":"","count":1}],"ทองคำ":[{"actor":"ผู้ยื่น","value":1347760,"type":"ทองคำ","name":"ทองคำรูปพรรณ น้ำหนักรวม 68 บาท","address":"","count":1},{"actor":"ผู้ยื่น","value":614420,"type":"ทองคำ","name":"ทองคำแท่ง น้ำหนักรวม 31 บาท","address":"","count":1}]},"เงินสด":[{"actor":"ผู้ยื่น","name":"เงินสด","value":4200000},{"actor":"คู่สมรส","name":"เงินสด","value":250000}],"เงินฝาก":[{"actor":"ผู้ยื่น","name":"เงินฝาก","value":2071816.48},{"actor":"คู่สมรส","name":"เงินฝาก","value":5182208.9},{"actor":"บุตร","name":"เงินฝาก","value":7040441.62}],"เงินลงทุน":[{"actor":"ผู้ยื่น","name":"เงินลงทุน","value":11736412.86},{"actor":"คู่สมรส","name":"เงินลงทุน","value":4178925.42}],"เงินให้กู้ยืม":[{"actor":"ผู้ยื่น","name":"เงินให้กู้ยืม","value":45362294.52}]}},"donation":[],"business":[],"statement":{"1":{"รายได้":[{"type":"รายได้ประจำ","value":[1374720,15496000,0]},{"type":"รายได้จากทรัพย์สิน","value":[2220025.28,22245.92,52308.97]},{"type":"รายได้จากการรับให้","value":[858000,10000000,0]},{"type":"รายได้อื่นๆ","value":[510632.93999999994,81468.33,0]}],"รายจ่าย":[{"type":"รายจ่ายประจำ","value":[3433900,10543578.5,2220446]},{"type":"รายจ่ายอื่นๆ","value":[1000000,5286700.53,0]}],"ทรัพย์สิน":[{"type":"เงินสด","value":[4200000,250000,0]},{"type":"เงินฝาก","value":[2071816.48,5182208.9,7040441.62]},{"type":"เงินลงทุน","value":[11736412.86,4178925.42,0]},{"type":"เงินให้กู้ยืม","value":[45362294.52,0,0]},{"type":"ที่ดิน","value":[32077500,117565000,0]},{"type":"โรงเรือนและสิ่งปลูกสร้าง","value":[111206460,8736620,0]},{"type":"ยานพาหนะ","value":[2818900,1198000,0]},{"type":"สิทธิและสัมปทาน","value":[10173084.88,7525666.51,3614617.17]},{"type":"ทรัพย์สินอื่น","value":[20429372,129865420,0]}],"หนี้สิน":[{"type":"เงินเบิกเกินบัญชี","value":[0,0,0]},{"type":"เงินกู้จากธนาคารและสถาบันการเงินอื่น","value":[45149407.88,15048957.34,0]},{"type":"หนี้สินที่มีหลักฐานเป็นหนังสือ","value":[0,3240929,0]},{"type":"หนี้สินอื่น","value":[0,63000000,0]}],"ภาษี":[45149407.88,81289886.34,0]}},"topAssets":{"1":{"actor":"ผู้ยื่น","value":104000000,"type":"โฉนด","name":"โฉนดที่ดิน","address":"คลองตัน พระโขนง กรุงเทพมหานคร","land_doc_number":16157,"receiveDate":"16/10/2561","baseCatg":"ที่ดิน"}},"latestStatement":{"year":2565,"รายได้":30615401.44,"รายจ่าย":22484625.03,"ทรัพย์สิน":525232740.36,"หนี้สิน":126439294.22}}