{"lawsuit":{"sec":[],"judgement":[],"nacc":[]},"relationship":[],"assets":{},"donation":[{"year":2554,"month":7,"party":"ประชาธิปัตย์","amount":100000},{"year":2554,"month":7,"party":"ประชาธิปัตย์","amount":50000}],"business":[{"position":"คณะกรรมการบริษัท","business_name":"บริษัท กุลธรอินเตอร์เนชั่นแนล จำกัด","type":"46599 การขายส่งเครื่องจักรและอุปกรณ์อื่นๆซึ่งมิได้จัดประเภทไว้ในที่อื่น"},{"position":"คณะกรรมการบริษัท","business_name":"บริษัท กุลธร จำกัด","type":"46421 การขายส่งเครื่องใช้ไฟฟ้าและอิเล็กทรอนิกส์ชนิดใช้ในครัวเรือน"}],"statement":{},"topAssets":{}}